kolibri_explore_plugin/VERSION
kolibri_explore_plugin/__init__.py
kolibri_explore_plugin/_version.py
kolibri_explore_plugin/api_urls.py
kolibri_explore_plugin/buildConfig.js
kolibri_explore_plugin/collectionviews.py
kolibri_explore_plugin/jobs.py
kolibri_explore_plugin/kolibri_plugin.py
kolibri_explore_plugin/models.py
kolibri_explore_plugin/options.py
kolibri_explore_plugin/tasks.py
kolibri_explore_plugin/urls.py
kolibri_explore_plugin/views.py
kolibri_explore_plugin/viewsets.py
kolibri_explore_plugin/apps/.gitkeep
kolibri_explore_plugin/assets/package.json
kolibri_explore_plugin/assets/src/apiResources.js
kolibri_explore_plugin/assets/src/app.js
kolibri_explore_plugin/assets/src/constants.js
kolibri_explore_plugin/assets/src/contentDownloadPlugin.js
kolibri_explore_plugin/assets/src/customApps.js
kolibri_explore_plugin/assets/src/index.scss
kolibri_explore_plugin/assets/src/intl-locale-data.js
kolibri_explore_plugin/assets/src/kolibriApi.js
kolibri_explore_plugin/assets/src/styles.scss
kolibri_explore_plugin/assets/src/vue-intl-locale-data.js
kolibri_explore_plugin/assets/src/components/AboutFooter.vue
kolibri_explore_plugin/assets/src/components/AboutModal.vue
kolibri_explore_plugin/assets/src/components/AlphabeticalChannelsList.vue
kolibri_explore_plugin/assets/src/components/DiscoveryNavBar.vue
kolibri_explore_plugin/assets/src/components/EkIguanaList.vue
kolibri_explore_plugin/assets/src/composables/useContentNodeProgress.js
kolibri_explore_plugin/assets/src/composables/useProgressTracking.js
kolibri_explore_plugin/assets/src/mixins/isOfflineMixin.js
kolibri_explore_plugin/assets/src/mixins/navigationMixin.js
kolibri_explore_plugin/assets/src/modules/pluginModule.js
kolibri_explore_plugin/assets/src/modules/coreExplore/actions.js
kolibri_explore_plugin/assets/src/modules/coreExplore/getters.js
kolibri_explore_plugin/assets/src/modules/coreExplore/mutations.js
kolibri_explore_plugin/assets/src/modules/coreExplore/utils.js
kolibri_explore_plugin-7.15.0.dist-info/LICENSE
kolibri_explore_plugin-7.15.0.dist-info/METADATA
kolibri_explore_plugin-7.15.0.dist-info/WHEEL
kolibri_explore_plugin-7.15.0.dist-info/entry_points.txt
kolibri_explore_plugin-7.15.0.dist-info/top_level.txt
kolibri_explore_plugin-7.15.0.dist-info/RECORD
