Metadata-Version: 2.1
Name: kolibri_explore_plugin
Version: 7.15.0
Summary: Kolibri plugin for Endless custom presentation
Author-email: Endless OS Foundation <key@endlessos.org>
License: MIT License
Project-URL: Homepage, https://github.com/endlessm/kolibri-explore-plugin
Project-URL: Bug Tracker, https://github.com/endlessm/kolibri-explore-plugin/issues/
Keywords: kolibri
Classifier: Development Status :: 2 - Pre-Alpha
Classifier: Intended Audience :: Developers
Classifier: License :: OSI Approved :: MIT License
Classifier: Natural Language :: English
Classifier: Programming Language :: Python :: 3
Classifier: Programming Language :: Python :: 3.3
Classifier: Programming Language :: Python :: 3.4
Classifier: Programming Language :: Python :: 3.5
Classifier: Programming Language :: Python :: Implementation :: PyPy
Requires-Python: >=3.3
License-File: LICENSE
